img2b64/__init__.py
img2b64/img2b64.py
i2b-2.2.1.dist-info/LICENSE
i2b-2.2.1.dist-info/METADATA
i2b-2.2.1.dist-info/WHEEL
i2b-2.2.1.dist-info/entry_points.txt
i2b-2.2.1.dist-info/top_level.txt
i2b-2.2.1.dist-info/RECORD
