Metadata-Version: 2.1
Name: i2b
Version: 2.2.1
Summary: Convert image into base64 string and store into the txt file
Home-page: https://github.com/sachinchavan9/image-encode-decode
Author: Sachin Chavan
Author-email: sachinewx@gmail.com
License: UNKNOWN
Keywords: image base64 jpg png jpeg JPG JPEG TIF
Platform: UNKNOWN
Classifier: Development Status :: 5 - Production/Stable
Classifier: Environment :: Console
Classifier: Intended Audience :: Developers
Classifier: Intended Audience :: Education
Classifier: Intended Audience :: Information Technology
Classifier: Natural Language :: English
Classifier: Operating System :: OS Independent
Classifier: Programming Language :: Python :: 2.7
Classifier: Programming Language :: Python :: 3.6
Classifier: Programming Language :: Python :: 3.7
Classifier: Programming Language :: Python :: 3.8
Classifier: Programming Language :: Python :: 3.9
Classifier: Topic :: Artistic Software
Classifier: License :: OSI Approved :: GNU General Public License v2 (GPLv2)
Requires-Python: >=2.7
